ttw_sdk/__init__.py
ttw_sdk/datetimes/__init__.py
ttw_sdk/datetimes/datetime_convert.py
ttw_tool_sdk-0.1.0.dist-info/METADATA
ttw_tool_sdk-0.1.0.dist-info/WHEEL
ttw_tool_sdk-0.1.0.dist-info/top_level.txt
ttw_tool_sdk-0.1.0.dist-info/RECORD
