Metadata-Version: 2.4
Name: ttw-tool-sdk
Version: 0.1.0
Summary: Add your description here
Requires-Python: >=3.11
Requires-Dist: tzdata==2025.2
